{
  "parse": {
    "title": "אברהם משה רבינוביץ'",
    "pageid": 39041,
    "text": {
      "*": "<div class=\"mw-content-rtl mw-parser-output\" lang=\"he\" dir=\"rtl\"><figure class=\"mw-default-size mw-halign-left\" typeof=\"mw:File/Thumb\"><a href=\"/index.php/%D7%A7%D7%95%D7%91%D7%A5:%D7%A1%D7%A7%D7%95%D7%9C%D7%99%D7%A2.JPG\" class=\"mw-file-description\"><img src=\"/images/thumb/8/8d/%D7%A1%D7%A7%D7%95%D7%9C%D7%99%D7%A2.JPG/220px-%D7%A1%D7%A7%D7%95%D7%9C%D7%99%D7%A2.JPG\" decoding=\"async\" width=\"220\" height=\"216\" class=\"mw-file-element\" srcset=\"/images/thumb/8/8d/%D7%A1%D7%A7%D7%95%D7%9C%D7%99%D7%A2.JPG/330px-%D7%A1%D7%A7%D7%95%D7%9C%D7%99%D7%A2.JPG 1.5x, /images/thumb/8/8d/%D7%A1%D7%A7%D7%95%D7%9C%D7%99%D7%A2.JPG/440px-%D7%A1%D7%A7%D7%95%D7%9C%D7%99%D7%A2.JPG 2x\" /></a><figcaption>האדמו\"ר</figcaption></figure>\n<p>רבי <b>אברהם משה רבינוביץ</b> (יליד שנת <a href=\"/index.php/%D7%AA%D7%A9%D7%9B%22%D7%90\" title=\"תשכ&quot;א\">תשכ\"א</a>) הוא האדמו\"ר מ<a href=\"/index.php/%D7%A1%D7%A7%D7%90%D7%9C%D7%99%D7%A2\" class=\"mw-redirect\" title=\"סקאליע\">סקאליע</a> המתגורר ב<a href=\"/index.php/%D7%91%D7%95%D7%A8%D7%95_%D7%A4%D7%90%D7%A8%D7%A7\" title=\"בורו פארק\">בורו פארק</a>.\n</p>\n<meta property=\"mw:PageProp/toc\" />\n<h2><span id=\".D7.AA.D7.95.D7.9C.D7.93.D7.95.D7.AA_.D7.97.D7.99.D7.99.D7.9D\"></span><span class=\"mw-headline\" id=\"תולדות_חיים\">תולדות חיים</span><span class=\"mw-editsection\"><span class=\"mw-editsection-bracket\">[</span><a href=\"/index.php?title=%D7%90%D7%91%D7%A8%D7%94%D7%9D_%D7%9E%D7%A9%D7%94_%D7%A8%D7%91%D7%99%D7%A0%D7%95%D7%91%D7%99%D7%A5%27&amp;veaction=edit&amp;section=1\" title=\"עריכת פסקה: &quot;תולדות חיים&quot;\" class=\"mw-editsection-visualeditor\"><span>עריכה</span></a><span class=\"mw-editsection-divider\"> | </span><a href=\"/index.php?title=%D7%90%D7%91%D7%A8%D7%94%D7%9D_%D7%9E%D7%A9%D7%94_%D7%A8%D7%91%D7%99%D7%A0%D7%95%D7%91%D7%99%D7%A5%27&amp;action=edit&amp;section=1\" title=\"עריכת קוד המקור של הפרק: תולדות חיים\"><span>עריכת קוד מקור</span></a><span class=\"mw-editsection-bracket\">]</span></span></h2>\n<p>נולד בשנת <a href=\"/index.php/%D7%AA%D7%A9%D7%9B%22%D7%90\" title=\"תשכ&quot;א\">תשכ\"א</a> ב<a href=\"/index.php/%D7%A7%D7%A8%D7%90%D7%95%D7%9F_%D7%94%D7%99%D7%99%D7%98%D7%A1\" title=\"קראון הייטס\">קראון הייטס</a> לאביו רבי יוסף ברוך פנחס רבינוביץ' בעל ה\"נעימות ברוך\", בנו חביבו של האדמו\"ר רבי <a href=\"/index.php/%D7%93%D7%95%D7%93_%D7%99%D7%A6%D7%97%D7%A7_%D7%90%D7%99%D7%99%D7%96%D7%99%D7%A7_%D7%A8%D7%91%D7%99%D7%A0%D7%95%D7%91%D7%99%D7%A5%27\" title=\"דוד יצחק אייזיק רבינוביץ&#39;\">דוד יצחק אייזיק רבינוביץ'</a> מסקאליע. \n</p><p>לאחר פטירת סבו האדמו\"ר מסקוליע, הוכתר על ידי החסידים ובני משפחתו להמשיך את האדמו\"רות. מאז מנהל את חצירו ברמה ב<a href=\"/index.php/%D7%91%D7%95%D7%A8%D7%95_%D7%A4%D7%90%D7%A8%D7%A7\" title=\"בורו פארק\">בורו פארק</a>. נודע כבעל מופת גדול וכבעל ידיעה עמוקה בספרי <a href=\"/index.php/%D7%A7%D7%91%D7%9C%D7%94\" class=\"mw-redirect\" title=\"קבלה\">קבלה</a> ונגלה.\n</p><p>סבו מצד אמו רבי לייבל ציוואק היה מקורב לחסידות חב\"ד ולמד בישיבת תומכי תמימים ליובאוויטש והיה מבין האוחזים את עמודי החופה של הרבי. הרבי החשיבו וכשהיה עובר לפניו היה מזכיר לו עובדה זו (כמו כן מוזכרת עובדה זו בשיחת הרבי אליו הנדפסת ב<a href=\"/index.php/%D7%A9%D7%99%D7%97%D7%95%D7%AA_%D7%A7%D7%95%D7%93%D7%A9\" title=\"שיחות קודש\">שיחות קודש</a>).\n</p>\n<h2><span id=\".D7.A2.D7.9D_.D7.94.D7.A8.D7.91.D7.99\"></span><span class=\"mw-headline\" id=\"עם_הרבי\">עם הרבי</span><span class=\"mw-editsection\"><span class=\"mw-editsection-bracket\">[</span><a href=\"/index.php?title=%D7%90%D7%91%D7%A8%D7%94%D7%9D_%D7%9E%D7%A9%D7%94_%D7%A8%D7%91%D7%99%D7%A0%D7%95%D7%91%D7%99%D7%A5%27&amp;veaction=edit&amp;section=2\" title=\"עריכת פסקה: &quot;עם הרבי&quot;\" class=\"mw-editsection-visualeditor\"><span>עריכה</span></a><span class=\"mw-editsection-divider\"> | </span><a href=\"/index.php?title=%D7%90%D7%91%D7%A8%D7%94%D7%9D_%D7%9E%D7%A9%D7%94_%D7%A8%D7%91%D7%99%D7%A0%D7%95%D7%91%D7%99%D7%A5%27&amp;action=edit&amp;section=2\" title=\"עריכת קוד המקור של הפרק: עם הרבי\"><span>עריכת קוד מקור</span></a><span class=\"mw-editsection-bracket\">]</span></span></h2>\n<p>היה מקורב לרבי וזכה להיכנס ל<a href=\"/index.php/%D7%99%D7%97%D7%99%D7%93%D7%95%D7%AA\" title=\"יחידות\">יחידות</a> עם הרבי, בה שאל את הרבי מספר שאלות עמוקות ב<a href=\"/index.php/%D7%A1%D7%A4%D7%A8_%D7%94%D7%AA%D7%A0%D7%99%D7%90\" title=\"ספר התניא\">ספר התניא</a>. במשך שיחתו עם הרבי בי\"ג תמוז <a href=\"/index.php/%D7%AA%D7%A9%D7%9E%22%D7%90\" title=\"תשמ&quot;א\">תשמ\"א</a> (שנדפסה ב<a href=\"/index.php/%D7%A9%D7%99%D7%97%D7%95%D7%AA_%D7%A7%D7%95%D7%93%D7%A9\" title=\"שיחות קודש\">שיחות קודש</a>) אמר הרבי מסקוליע לרבי כי הוא צאצא של הבעל שם טוב. הרבי אמר לו כי גם נכד של תלמיד נחשב כנכד, והלא <a href=\"/index.php/%D7%90%D7%93%D7%9E%D7%95%22%D7%A8_%D7%94%D7%96%D7%A7%D7%9F\" class=\"mw-redirect\" title=\"אדמו&quot;ר הזקן\">אדמו\"ר הזקן</a> היה נכד רוחני של הבעל שם טוב. אך הודה לו כי יש מעלה מיוחדת בנכד העדיפה על של תלמיד. הרב חודוקוב אמר להרב באלקני שהרבי הורה למשמשיו כי בכל עת שיבא האדמו\"ר יש להכניסו ללא כל שיהוי (למרות שהאדמו\"ר היה אז בסביבות גיל עשרים).\n</p>\n<h2><span id=\".D7.A1.D7.A4.D7.A8.D7.99.D7.95\"></span><span class=\"mw-headline\" id=\"ספריו\">ספריו</span><span class=\"mw-editsection\"><span class=\"mw-editsection-bracket\">[</span><a href=\"/index.php?title=%D7%90%D7%91%D7%A8%D7%94%D7%9D_%D7%9E%D7%A9%D7%94_%D7%A8%D7%91%D7%99%D7%A0%D7%95%D7%91%D7%99%D7%A5%27&amp;veaction=edit&amp;section=3\" title=\"עריכת פסקה: &quot;ספריו&quot;\" class=\"mw-editsection-visualeditor\"><span>עריכה</span></a><span class=\"mw-editsection-divider\"> | </span><a href=\"/index.php?title=%D7%90%D7%91%D7%A8%D7%94%D7%9D_%D7%9E%D7%A9%D7%94_%D7%A8%D7%91%D7%99%D7%A0%D7%95%D7%91%D7%99%D7%A5%27&amp;action=edit&amp;section=3\" title=\"עריכת קוד המקור של הפרק: ספריו\"><span>עריכת קוד מקור</span></a><span class=\"mw-editsection-bracket\">]</span></span></h2>\n<ul><li>חכימא ברמיזא (על התורה)</li>\n<li>חיים לכל חי (ברית מילה)</li>\n<li>עטרת דוד (תורה ומועדים)</li>\n<li>ובחרת בחיים (מוסר והשקפה)</li>\n<li>הדרת מלך (ראש השנה)</li>\n<li>בלילה שירה עימי (פסח)</li>\n<li>ושכנתי בתוכם (הלכות בית הבחירה)</li>\n<li>אמירה נעימה (ד\"ת מדי שבת בשבתו במשך שנים רבות)</li>\n<li>דבר נאה ומתקבל (נישואין)</li>\n<li>כוננת מאז (נישואין)</li></ul>\n<h2><span id=\".D7.A7.D7.99.D7.A9.D7.95.D7.A8.D7.99.D7.9D_.D7.97.D7.99.D7.A6.D7.95.D7.A0.D7.99.D7.99.D7.9D\"></span><span class=\"mw-headline\" id=\"קישורים_חיצוניים\">קישורים חיצוניים</span><span class=\"mw-editsection\"><span class=\"mw-editsection-bracket\">[</span><a href=\"/index.php?title=%D7%90%D7%91%D7%A8%D7%94%D7%9D_%D7%9E%D7%A9%D7%94_%D7%A8%D7%91%D7%99%D7%A0%D7%95%D7%91%D7%99%D7%A5%27&amp;veaction=edit&amp;section=4\" title=\"עריכת פסקה: &quot;קישורים חיצוניים&quot;\" class=\"mw-editsection-visualeditor\"><span>עריכה</span></a><span class=\"mw-editsection-divider\"> | </span><a href=\"/index.php?title=%D7%90%D7%91%D7%A8%D7%94%D7%9D_%D7%9E%D7%A9%D7%94_%D7%A8%D7%91%D7%99%D7%A0%D7%95%D7%91%D7%99%D7%A5%27&amp;action=edit&amp;section=4\" title=\"עריכת קוד המקור של הפרק: קישורים חיצוניים\"><span>עריכת קוד מקור</span></a><span class=\"mw-editsection-bracket\">]</span></span></h2>\n<ul><li><a rel=\"nofollow\" class=\"external text\" href=\"https://hebrewbooks.org/pdfpager.aspx?req=4629&amp;st=&amp;pgnum=791&amp;hilite=\">שיחות קודש תשמ\"א</a> שיחת הרבי עם האדמו\"ר מסקוליע <span typeof=\"mw:File\"><a href=\"/index.php/%D7%94%D7%99%D7%91%D7%A8%D7%95%D7%91%D7%95%D7%A7%D7%A1\" title=\"היברובוקס\"><img src=\"/images/thumb/9/93/%D7%94%D7%91.jpg/23px-%D7%94%D7%91.jpg\" decoding=\"async\" width=\"23\" height=\"25\" class=\"mw-file-element\" srcset=\"/images/thumb/9/93/%D7%94%D7%91.jpg/35px-%D7%94%D7%91.jpg 1.5x, /images/thumb/9/93/%D7%94%D7%91.jpg/46px-%D7%94%D7%91.jpg 2x\" /></a></span></li></ul>\n<!-- \nNewPP limit report\nCached time: 20260414030830\nCache expiry: 86400\nReduced expiry: false\nComplications: [show‐toc]\nCPU time usage: 0.015 seconds\nReal time usage: 0.022 seconds\nPreprocessor visited node count: 28/1000000\nPost‐expand include size: 59/2097152 bytes\nTemplate argument size: 0/2097152 bytes\nHighest expansion depth: 2/100\nExpensive parser function count: 0/100\nUnstrip recursion depth: 0/20\nUnstrip post‐expand size: 0/5000000 bytes\n-->\n<!--\nTransclusion expansion time report (%,ms,calls,template)\n100.00%    2.634      1 תבנית:הב\n100.00%    2.634      1 -total\n-->\n\n<!-- Saved in parser cache with key chabadped_1-infopedia_:pcache:idhash:39041-0!canonical and timestamp 20260414030830 and revision id 703115. Rendering was triggered because: api-parse\n -->\n</div>"
    },
    "categories": [
      {
        "sortkey": "",
        "*": "אדמו\"רים"
      },
      {
        "sortkey": "",
        "*": "ידידי_חב\"ד"
      },
      {
        "sortkey": "",
        "*": "אישים_שנולדו_בשנת_תשכ\"א"
      }
    ],
    "links": [
      {
        "ns": 0,
        "exists": "",
        "*": "היברובוקס"
      },
      {
        "ns": 0,
        "exists": "",
        "*": "אדמו\"ר הזקן"
      },
      {
        "ns": 0,
        "exists": "",
        "*": "בורו פארק"
      },
      {
        "ns": 0,
        "exists": "",
        "*": "דוד יצחק אייזיק רבינוביץ'"
      },
      {
        "ns": 0,
        "exists": "",
        "*": "יחידות"
      },
      {
        "ns": 0,
        "exists": "",
        "*": "ספר התניא"
      },
      {
        "ns": 0,
        "exists": "",
        "*": "סקאליע"
      },
      {
        "ns": 0,
        "exists": "",
        "*": "קבלה"
      },
      {
        "ns": 0,
        "exists": "",
        "*": "קראון הייטס"
      },
      {
        "ns": 0,
        "exists": "",
        "*": "שיחות קודש"
      },
      {
        "ns": 0,
        "exists": "",
        "*": "תשכ\"א"
      },
      {
        "ns": 0,
        "exists": "",
        "*": "תשמ\"א"
      }
    ],
    "sections": [
      {
        "toclevel": 1,
        "level": "2",
        "line": "תולדות חיים",
        "number": "1",
        "index": "1",
        "fromtitle": "אברהם_משה_רבינוביץ'",
        "byteoffset": 139,
        "anchor": "תולדות_חיים",
        "linkAnchor": "תולדות_חיים"
      },
      {
        "toclevel": 1,
        "level": "2",
        "line": "עם הרבי",
        "number": "2",
        "index": "2",
        "fromtitle": "אברהם_משה_רבינוביץ'",
        "byteoffset": 746,
        "anchor": "עם_הרבי",
        "linkAnchor": "עם_הרבי"
      },
      {
        "toclevel": 1,
        "level": "2",
        "line": "ספריו",
        "number": "3",
        "index": "3",
        "fromtitle": "אברהם_משה_רבינוביץ'",
        "byteoffset": 1253,
        "anchor": "ספריו",
        "linkAnchor": "ספריו"
      },
      {
        "toclevel": 1,
        "level": "2",
        "line": "קישורים חיצוניים",
        "number": "4",
        "index": "4",
        "fromtitle": "אברהם_משה_רבינוביץ'",
        "byteoffset": 1537,
        "anchor": "קישורים_חיצוניים",
        "linkAnchor": "קישורים_חיצוניים"
      }
    ],
    "showtoc": ""
  }
}