{
  "parse": {
    "title": "אהרן טננבוים",
    "pageid": 66105,
    "text": {
      "*": "<div class=\"mw-content-rtl mw-parser-output\" lang=\"he\" dir=\"rtl\"><figure class=\"mw-default-size mw-halign-left\" typeof=\"mw:File/Thumb\"><a href=\"/index.php/%D7%A7%D7%95%D7%91%D7%A5:%D7%90%27_%D7%98%D7%A0%D7%A0%D7%91%D7%95%D7%99%D7%9D.png\" class=\"mw-file-description\"><img src=\"/images/5/54/%D7%90%27_%D7%98%D7%A0%D7%A0%D7%91%D7%95%D7%99%D7%9D.png\" decoding=\"async\" width=\"183\" height=\"278\" class=\"mw-file-element\" /></a><figcaption>ארי טננבוים</figcaption></figure>\n<p>ר' <b>אהרן</b> (ארי) <b>טננבוים</b> (יליד שנת <a href=\"/index.php/%D7%AA%D7%A9%D7%A0%22%D7%98\" title=\"תשנ&quot;ט\">תשנ\"ט</a>, 1999) שימש בעברו כאיש תקשורת חב\"די, בין היתר היה כתב באתר החדשות 'כיכר השבת'. עורך את רשת קבוצות הוואצפ 'מאחורי הקלעים בחב\"ד'. מנהל משרד הפרסום \"כתום\".\n</p>\n<h2><span id=\".D7.AA.D7.95.D7.9C.D7.93.D7.95.D7.AA_.D7.97.D7.99.D7.99.D7.9D\"></span><span class=\"mw-headline\" id=\"תולדות_חיים\">תולדות חיים</span><span class=\"mw-editsection\"><span class=\"mw-editsection-bracket\">[</span><a href=\"/index.php?title=%D7%90%D7%94%D7%A8%D7%9F_%D7%98%D7%A0%D7%A0%D7%91%D7%95%D7%99%D7%9D&amp;veaction=edit&amp;section=1\" title=\"עריכת פסקה: &quot;תולדות חיים&quot;\" class=\"mw-editsection-visualeditor\"><span>עריכה</span></a><span class=\"mw-editsection-divider\"> | </span><a href=\"/index.php?title=%D7%90%D7%94%D7%A8%D7%9F_%D7%98%D7%A0%D7%A0%D7%91%D7%95%D7%99%D7%9D&amp;action=edit&amp;section=1\" title=\"עריכת קוד המקור של הפרק: תולדות חיים\"><span>עריכת קוד מקור</span></a><span class=\"mw-editsection-bracket\">]</span></span></h2>\n<p>נולד ב<a href=\"/index.php/%D7%9B%22%D7%90_%D7%9E%D7%A0%D7%97%D7%9D_%D7%90%D7%91\" class=\"mw-redirect\" title=\"כ&quot;א מנחם אב\">כ\"א מנחם אב</a> <a href=\"/index.php/%D7%94%27%D7%AA%D7%A9%D7%A0%22%D7%98\" class=\"mw-redirect\" title=\"ה&#39;תשנ&quot;ט\">ה'תשנ\"ט</a>, גר בילדותו ב<a href=\"/index.php/%D7%99%D7%A8%D7%95%D7%A9%D7%9C%D7%99%D7%9D\" title=\"ירושלים\">ירושלים</a>.\n</p><p>למד ב<a href=\"/index.php/%D7%AA%D7%9C%D7%9E%D7%95%D7%93_%D7%AA%D7%95%D7%A8%D7%94_%D7%AA%D7%95%D7%A8%D7%AA_%D7%90%D7%9E%D7%AA_%D7%99%D7%A8%D7%95%D7%A9%D7%9C%D7%99%D7%9D\" title=\"תלמוד תורה תורת אמת ירושלים\">תלמוד תורה תורת אמת ירושלים</a> ולאחר מכן ב<a href=\"/index.php/%D7%AA%D7%95%D7%9E%D7%9B%D7%99_%D7%AA%D7%9E%D7%99%D7%9E%D7%99%D7%9D_%D7%A7%D7%A8%D7%99%D7%AA_%D7%92%D7%AA_(%D7%92%D7%93%D7%95%D7%9C%D7%94)\" class=\"mw-redirect\" title=\"תומכי תמימים קרית גת (גדולה)\">תות\"ל קרית גת</a> בישיבה <a href=\"/index.php/%D7%AA%D7%95%D7%9E%D7%9B%D7%99_%D7%AA%D7%9E%D7%99%D7%9E%D7%99%D7%9D_%D7%A7%D7%A8%D7%99%D7%AA_%D7%92%D7%AA_(%D7%A7%D7%98%D7%A0%D7%94)\" class=\"mw-redirect\" title=\"תומכי תמימים קרית גת (קטנה)\"> קטנה</a> וגדולה. את שיעור ג' עשה ב<a href=\"/index.php/%D7%AA%D7%95%D7%9E%D7%9B%D7%99_%D7%AA%D7%9E%D7%99%D7%9E%D7%99%D7%9D_%D7%9B%D7%A4%D7%A8_%D7%97%D7%91%22%D7%93\" title=\"תומכי תמימים כפר חב&quot;ד\">תומכי תמימים כפר חב\"ד</a>. בהמשך שימש כמדריך בפנימיית \"<a href=\"/index.php/%D7%90%D7%95%D7%A8_%D7%A9%D7%9E%D7%97%D7%94\" class=\"mw-redirect\" title=\"אור שמחה\">אור שמחה</a>\" ב<a href=\"/index.php/%D7%9B%D7%A4%D7%A8_%D7%97%D7%91%22%D7%93\" title=\"כפר חב&quot;ד\">כפר חב\"ד</a>. \n</p><p>בשנת <a href=\"/index.php/%D7%AA%D7%A9%D7%A2%22%D7%98\" title=\"תשע&quot;ט\">תשע\"ט</a> התחתן עם רעייתו לבית משפחת גורדין וקבע את מושבו בעיר <a href=\"/index.php/%D7%91%D7%99%D7%AA%D7%A8_%D7%A2%D7%99%D7%9C%D7%99%D7%AA\" title=\"ביתר עילית\">ביתר עילית</a>.\n</p><p>לאחר שנה בה שימש כמחנך ב<a href=\"/index.php/%D7%AA%D7%9C%D7%9E%D7%95%D7%93_%D7%AA%D7%95%D7%A8%D7%94_%D7%AA%D7%95%D7%A8%D7%AA_%D7%90%D7%9E%D7%AA_%D7%99%D7%A8%D7%95%D7%A9%D7%9C%D7%99%D7%9D\" title=\"תלמוד תורה תורת אמת ירושלים\">תלמוד תורה תורת אמת ירושלים</a> לצד ניהול סניף <a href=\"/index.php/%D7%90%D7%A8%D7%92%D7%95%D7%9F_%D7%94%D7%A4%D7%A0%D7%A1%D7%90%D7%99%D7%9D\" title=\"ארגון הפנסאים\">פנסאים</a> ב<a href=\"/index.php/%D7%91%D7%99%D7%AA%D7%A8_%D7%A2%D7%99%D7%9C%D7%99%D7%AA\" title=\"ביתר עילית\">ביתר עילית</a>, פנה לתחום התקשורת החב\"דית והחל לערוך את אתר החדשות החב\"די '<a href=\"/index.php/%D7%A9%D7%98%D7%95%D7%A8%D7%A2%D7%9D.%D7%A0%D7%98\" class=\"mw-redirect\" title=\"שטורעם.נט\">שטורעם.נט</a>' במשך תקופה, לאחר מכן היה לעורך ראשי באתר 'חב\"ד ניוז'. משם פנה לתקשורת החרדית והיה לעורך באתר 'קול חי', מבית רדיו קול חי.\n</p><p>טננבוים נחשב מומחה לאומנות הדיבור ובין היתר מפרסם ברשת סרטוני \"אריטוריקה\" עם מגוון טיפים ועצות באומנות הדיבור מול קהל תוך שהוא משלב מסרים מפרשת השבוע.\n</p><p>כמו כן, חיבר את הקובץ \"חתונה לחיים\" ובו מגוון טיפים ועצות מעשיות לתמים מהרגע שהוא ניגש לשידוכים ועד לחתונה, הקובץ תפס תאוצה ורבים מהבחורים קוראים אותו טרם הם נכנסים לעולם השידוכים.\n</p><p>בעברו משמש ככתב מגזין ושיווק באתר החדשות החרדי \"כיכר השבת\", כתב בעיתון השבועי 'מרכז העניינים' וכן מפעיל את רשת קבוצות הוואצפ \"מאחורי הקלעים בחב\"ד\". \n</p><p>חלק מכתבות המגזין שפרסם צברו תאוצה בעולם החרדי והפכו לפופולריות ביותר כמו ראיון עם סבו הרב <a href=\"/index.php/%D7%9E%D7%A0%D7%97%D7%9D_%D7%9E%D7%A2%D7%A0%D7%93%D7%9C_%D7%98%D7%A0%D7%A0%D7%91%D7%95%D7%99%D7%9D\" title=\"מנחם מענדל טננבוים\">מענדל טננבוים</a> על פיענוח ספרי ה<a href=\"/index.php/%D7%A8%D7%95%D7%92%D7%95%D7%A6%27%D7%95%D7%91%D7%A8\" class=\"mw-redirect\" title=\"רוגוצ&#39;ובר\">רוגוצ'ובר</a>, כתבה עם סוחרי גת, אנשים שברחו לחו\"ל בעקבות השקעות כספיות מסוכנות, אנשים שזכו בלוטו והפסידו את כספם ועוד.\n</p><p>בשנת <a href=\"/index.php/%D7%AA%D7%A9%D7%A4%22%D7%91\" title=\"תשפ&quot;ב\">תשפ\"ב</a> פרסם פודקאסט \"הליטאי והחב\"דניק\" בן ארבעה פרקים, יחד עם כתב כיכר השבת ישראל גינצבורג, ובו דנו על הבדלי השקפות בין העולם הליטאי לעולם החסידי והחב\"די.\n</p><p>בנוסף, כתב למשרדי פרסום ועיתונים חרדיים מעת לעת לצד עבודות כתיבה מקצועיות לשוק הפרטי. בהמשך הקים את משרד הפרסום \"כתום\". תקופה קצרה שימש כקופירייטר במשרד הפרסום 'גל אורן' אך בהמשך עזב לשוק הפרטי.\n</p>\n<!-- \nNewPP limit report\nCached time: 20260414031610\nCache expiry: 86400\nReduced expiry: false\nComplications: []\nCPU time usage: 0.043 seconds\nReal time usage: 0.067 seconds\nPreprocessor visited node count: 5/1000000\nPost‐expand include size: 0/2097152 bytes\nTemplate argument size: 0/2097152 bytes\nHighest expansion depth: 2/100\nExpensive parser function count: 0/100\nUnstrip recursion depth: 0/20\nUnstrip post‐expand size: 0/5000000 bytes\n-->\n<!--\nTransclusion expansion time report (%,ms,calls,template)\n100.00%    0.000      1 -total\n-->\n\n<!-- Saved in parser cache with key chabadped_1-infopedia_:pcache:idhash:66105-0!canonical and timestamp 20260414031610 and revision id 779967. Rendering was triggered because: api-parse\n -->\n</div>"
    },
    "categories": [
      {
        "sortkey": "",
        "*": "חסידים_בתקופת_אדמו\"ר_שליט\"א"
      },
      {
        "sortkey": "",
        "*": "אישים_שנולדו_בשנת_תשנ\"ט"
      },
      {
        "sortkey": "",
        "*": "אנשי_תקשורת"
      },
      {
        "sortkey": "",
        "*": "אישים_בביתר_עילית"
      },
      {
        "sortkey": "",
        "*": "בוגרי_תומכי_תמימים_קריית_גת"
      },
      {
        "sortkey": "",
        "*": "בוגרי_תומכי_תמימים_כפר_חב\"ד"
      },
      {
        "sortkey": "",
        "*": "משפחת_גופין"
      }
    ],
    "links": [
      {
        "ns": 0,
        "exists": "",
        "*": "אור שמחה"
      },
      {
        "ns": 0,
        "exists": "",
        "*": "ארגון הפנסאים"
      },
      {
        "ns": 0,
        "exists": "",
        "*": "ביתר עילית"
      },
      {
        "ns": 0,
        "exists": "",
        "*": "ה'תשנ\"ט"
      },
      {
        "ns": 0,
        "exists": "",
        "*": "ירושלים"
      },
      {
        "ns": 0,
        "exists": "",
        "*": "כ\"א מנחם אב"
      },
      {
        "ns": 0,
        "exists": "",
        "*": "כפר חב\"ד"
      },
      {
        "ns": 0,
        "exists": "",
        "*": "מנחם מענדל טננבוים"
      },
      {
        "ns": 0,
        "exists": "",
        "*": "רוגוצ'ובר"
      },
      {
        "ns": 0,
        "exists": "",
        "*": "שטורעם.נט"
      },
      {
        "ns": 0,
        "exists": "",
        "*": "תומכי תמימים כפר חב\"ד"
      },
      {
        "ns": 0,
        "exists": "",
        "*": "תומכי תמימים קרית גת (גדולה)"
      },
      {
        "ns": 0,
        "exists": "",
        "*": "תומכי תמימים קרית גת (קטנה)"
      },
      {
        "ns": 0,
        "exists": "",
        "*": "תלמוד תורה תורת אמת ירושלים"
      },
      {
        "ns": 0,
        "exists": "",
        "*": "תשנ\"ט"
      },
      {
        "ns": 0,
        "exists": "",
        "*": "תשע\"ט"
      },
      {
        "ns": 0,
        "exists": "",
        "*": "תשפ\"ב"
      }
    ],
    "sections": [
      {
        "toclevel": 1,
        "level": "2",
        "line": "תולדות חיים",
        "number": "1",
        "index": "1",
        "fromtitle": "אהרן_טננבוים",
        "byteoffset": 256,
        "anchor": "תולדות_חיים",
        "linkAnchor": "תולדות_חיים"
      }
    ]
  }
}