{
  "parse": {
    "title": "טייכטל (פירושונים)",
    "pageid": 75056,
    "text": {
      "*": "<div class=\"mw-content-rtl mw-parser-output\" lang=\"he\" dir=\"rtl\"><p><b>האם התכוונתם ל...</b><br />\n</p>\n<div class=\"nodisambig\">\n<ul><li>הרב <a href=\"/index.php/%D7%97%D7%99%D7%99%D7%9D_%D7%9E%D7%A0%D7%97%D7%9D_%D7%98%D7%99%D7%99%D7%9B%D7%98%D7%9C\" title=\"חיים מנחם טייכטל\">חיים מנחם טייכטל</a> - מחנך ותיק ומוערך ב<a href=\"/index.php/%D7%99%D7%A8%D7%95%D7%A9%D7%9C%D7%99%D7%9D\" title=\"ירושלים\">ירושלים</a>, ומחבר ספרי לימוד לילדים.</li>\n<li>הרב <a href=\"/index.php/%D7%93%D7%95%D7%93_%D7%98%D7%99%D7%99%D7%9B%D7%98%D7%9C\" title=\"דוד טייכטל\">דוד טייכטל</a> - שליח ומשפיע קהילת חב\"ד ב<a href=\"/index.php/%D7%A0%D7%95%D7%A3_%D7%94%D7%92%D7%9C%D7%99%D7%9C\" title=\"נוף הגליל\">נוף הגליל</a>, וראש כולל \"תפארת מנחם\" בעיר.</li>\n<li>הרב <a href=\"/index.php/%D7%99%D7%95%D7%A1%D7%A3_%D7%99%D7%A6%D7%97%D7%A7_%D7%9E%D7%90%D7%99%D7%A8_%D7%98%D7%99%D7%99%D7%9B%D7%98%D7%9C\" title=\"יוסף יצחק מאיר טייכטל\">יוסף יצחק מאיר טייכטל</a> - רב קהילת חב\"ד אוברוויליע וחבר ועד רבני ליובאוויטש צרפת, משמש כראש כולל 'יד מרדכי' ב<a href=\"/index.php/%D7%A4%D7%A8%D7%99%D7%96\" title=\"פריז\">פריז</a>.</li>\n<li>הרב <a href=\"/index.php/%D7%99%D7%A9%D7%A9%D7%9B%D7%A8_%D7%A9%D7%9C%D7%9E%D7%94_%D7%98%D7%99%D7%99%D7%9B%D7%98%D7%9C\" title=\"יששכר שלמה טייכטל\">יששכר שלמה טייכטל</a> - משפיע ומחנך ב<a href=\"/index.php/%D7%A7%D7%A8%D7%90%D7%95%D7%9F_%D7%94%D7%99%D7%99%D7%98%D7%A1\" title=\"קראון הייטס\">קראון הייטס</a>, חבר סגל ההוראה ב'ישיבה יוניברסיטי'.</li>\n<li>הרב <a href=\"/index.php/%D7%99%D7%94%D7%95%D7%93%D7%94_%D7%90%D7%9C%D7%99%D7%A7%D7%99%D7%9D_%D7%98%D7%99%D7%99%D7%9B%D7%98%D7%9C\" class=\"mw-redirect\" title=\"יהודה אליקים טייכטל\">יהודה אליקים טייכטל</a> - רבה הראשי של <a href=\"/index.php/%D7%91%D7%A8%D7%9C%D7%99%D7%9F\" title=\"ברלין\">ברלין</a>, שליח הרבי ועומד בראש המרכז החינוכי היהודי חב\"ד בברלין.</li>\n<li>הרב <a href=\"/index.php?title=%D7%97%D7%A0%D7%9F_%D7%98%D7%99%D7%99%D7%9B%D7%98%D7%9C&amp;action=edit&amp;redlink=1\" class=\"new\" title=\"חנן טייכטל (הדף אינו קיים)\">חנן טייכטל</a> - <a href=\"/index.php/%D7%A8%22%D7%9E\" class=\"mw-redirect\" title=\"ר&quot;מ\">ר\"מ</a> ו<a href=\"/index.php/%D7%9E%D7%A9%D7%A4%D7%99%D7%A2\" title=\"משפיע\">משפיע</a> ב<a href=\"/index.php/%D7%AA%D7%95%D7%AA%22%D7%9C_%D7%9E%D7%95%D7%A1%D7%A7%D7%91%D7%94\" class=\"mw-redirect\" title=\"תות&quot;ל מוסקבה\">ישיבה קטנה</a> ב<a href=\"/index.php/%D7%9E%D7%95%D7%A1%D7%A7%D7%91%D7%94\" title=\"מוסקבה\">מוסקבה</a>.</li></ul>\n</div>\n<table class=\"plainlinks dmbox dmbox-disambig\" style=\"width: 100%; margin-top: 10px; border-top: 1px solid #aaa;\">\n\n<tbody><tr>\n<td style=\"vertical-align: top; padding-top: 0.6em;\"><figure class=\"mw-halign-right\" typeof=\"mw:File\"><a href=\"/index.php/%D7%A7%D7%95%D7%91%D7%A5:Disambig_RTL.svg\" class=\"mw-file-description\" title=\"פירושונים\"><img alt=\"פירושונים\" src=\"/images/thumb/b/bc/Disambig_RTL.svg/40px-Disambig_RTL.svg.png\" decoding=\"async\" width=\"40\" height=\"31\" class=\"mw-file-element\" srcset=\"/images/thumb/b/bc/Disambig_RTL.svg/60px-Disambig_RTL.svg.png 1.5x, /images/thumb/b/bc/Disambig_RTL.svg/80px-Disambig_RTL.svg.png 2x\" /></a><figcaption>פירושונים</figcaption></figure> </td><td class=\"mbox-text\" style=\"padding: 0.25em 0.4em\"> זהו דף <a href=\"/index.php/%D7%97%D7%91%22%D7%93%D7%A4%D7%93%D7%99%D7%94:%D7%A4%D7%99%D7%A8%D7%95%D7%A9%D7%95%D7%A0%D7%99%D7%9D\" title=\"חב&quot;דפדיה:פירושונים\">פירושונים</a>, שמטרתו להבחין בין ערכים שונים בעלי שם דומה.\n<div class=\"checkty-ignore\">\n<p><span typeof=\"mw:File\"><a href=\"/index.php/%D7%A7%D7%95%D7%91%D7%A5:Gnome-searchtool.svg\" class=\"mw-file-description\"><img src=\"/images/thumb/1/1e/Gnome-searchtool.svg/21px-Gnome-searchtool.svg.png\" decoding=\"async\" width=\"21\" height=\"21\" class=\"mw-file-element\" srcset=\"/images/thumb/1/1e/Gnome-searchtool.svg/32px-Gnome-searchtool.svg.png 1.5x, /images/thumb/1/1e/Gnome-searchtool.svg/42px-Gnome-searchtool.svg.png 2x\" /></a></span> אם לא מצאתם ברשימת הפירושונים את הערך שהתכוונתם אליו, נסו:\n</p>\n<ul><li><a href=\"/index.php/%D7%9E%D7%99%D7%95%D7%97%D7%93:%D7%93%D7%A4%D7%99%D7%9D_%D7%94%D7%9E%D7%AA%D7%97%D7%99%D7%9C%D7%99%D7%9D_%D7%91/%D7%98%D7%99%D7%99%D7%9B%D7%98%D7%9C\" title=\"מיוחד:דפים המתחילים ב/טייכטל\">דפים ששמם מתחיל ב”טייכטל“</a></li>\n<li><a href=\"/index.php/%D7%9E%D7%99%D7%95%D7%97%D7%93:%D7%97%D7%99%D7%A4%D7%95%D7%A9/intitle:%D7%98%D7%99%D7%99%D7%9B%D7%98%D7%9C%22\" title=\"מיוחד:חיפוש/intitle:טייכטל&quot;\">דפים ששמם מכיל ”טייכטל“</a></li>\n<li><a href=\"/index.php/%D7%9E%D7%99%D7%95%D7%97%D7%93:%D7%97%D7%99%D7%A4%D7%95%D7%A9/~%22%D7%98%D7%99%D7%99%D7%9B%D7%98%D7%9C%22\" title=\"מיוחד:חיפוש/~&quot;טייכטל&quot;\">חיפוש ”טייכטל“ בחב\"דפדיה</a></li></ul>\n</div>\n</td>\n</tr></tbody></table>\n<!-- \nNewPP limit report\nCached time: 20260413183559\nCache expiry: 86400\nReduced expiry: false\nComplications: []\nCPU time usage: 0.049 seconds\nReal time usage: 0.312 seconds\nPreprocessor visited node count: 63/1000000\nPost‐expand include size: 2688/2097152 bytes\nTemplate argument size: 1166/2097152 bytes\nHighest expansion depth: 9/100\nExpensive parser function count: 2/100\nUnstrip recursion depth: 0/20\nUnstrip post‐expand size: 0/5000000 bytes\nLua time usage: 0.030/7 seconds\nLua virtual size: 5369856/52428800 bytes\nLua estimated memory usage: 0 bytes\n-->\n<!--\nTransclusion expansion time report (%,ms,calls,template)\n100.00%  274.014      1 תבנית:פירושונים\n100.00%  274.014      1 -total\n 20.08%   55.022      1 תבנית:פירושונים/חיפושים\n 11.82%   32.396      1 תבנית:שם_הדף_בלי_הסוגריים\n  7.82%   21.434      1 תבנית:בלי_הסוגריים\n  4.87%   13.336      1 תבנית:קטגוריה_בתבנית\n-->\n\n<!-- Saved in parser cache with key chabadped_1-infopedia_:pcache:idhash:75056-0!canonical and timestamp 20260413183559 and revision id 829602. Rendering was triggered because: page-view\n -->\n</div>"
    },
    "categories": [
      {
        "sortkey": "טייכטל (פירושונים)",
        "*": "פירושונים"
      }
    ],
    "links": [
      {
        "ns": 10,
        "exists": "",
        "*": "תבנית:פירושונים"
      },
      {
        "ns": 10,
        "exists": "",
        "*": "תבנית:פירושונים/חיפושים"
      },
      {
        "ns": 0,
        "exists": "",
        "*": "ברלין"
      },
      {
        "ns": 0,
        "exists": "",
        "*": "דוד טייכטל"
      },
      {
        "ns": 0,
        "exists": "",
        "*": "חיים מנחם טייכטל"
      },
      {
        "ns": 0,
        "exists": "",
        "*": "יהודה אליקים טייכטל"
      },
      {
        "ns": 0,
        "exists": "",
        "*": "יוסף יצחק מאיר טייכטל"
      },
      {
        "ns": 0,
        "exists": "",
        "*": "ירושלים"
      },
      {
        "ns": 0,
        "exists": "",
        "*": "יששכר שלמה טייכטל"
      },
      {
        "ns": 0,
        "exists": "",
        "*": "מוסקבה"
      },
      {
        "ns": 0,
        "exists": "",
        "*": "משפיע"
      },
      {
        "ns": 0,
        "exists": "",
        "*": "נוף הגליל"
      },
      {
        "ns": 0,
        "exists": "",
        "*": "פריז"
      },
      {
        "ns": 0,
        "exists": "",
        "*": "קראון הייטס"
      },
      {
        "ns": 0,
        "exists": "",
        "*": "ר\"מ"
      },
      {
        "ns": 0,
        "exists": "",
        "*": "תות\"ל מוסקבה"
      },
      {
        "ns": 0,
        "*": "חנן טייכטל"
      },
      {
        "ns": 4,
        "exists": "",
        "*": "חב\"דפדיה:פירושונים"
      }
    ],
    "sections": []
  }
}