{
  "parse": {
    "title": "יצחק גנזבורג",
    "pageid": 7840,
    "text": {
      "*": "<div class=\"mw-content-rtl mw-parser-output\" lang=\"he\" dir=\"rtl\"><div class=\"noexcerpt noprint\" style=\"font-size: 90%; color: #555577; margin-right: 22px;\"><span typeof=\"mw:File\"><span><img src=\"/images/thumb/b/bc/Disambig_RTL.svg/25px-Disambig_RTL.svg.png\" decoding=\"async\" width=\"25\" height=\"19\" class=\"mw-file-element\" srcset=\"/images/thumb/b/bc/Disambig_RTL.svg/38px-Disambig_RTL.svg.png 1.5x, /images/thumb/b/bc/Disambig_RTL.svg/50px-Disambig_RTL.svg.png 2x\" /></span></span> <span class=\"nodisambig\">המונח \"יצחק גינזבורג\" מפנה לכאן. אם הכוונה למשמעות אחרת, ראו <a href=\"/index.php/%D7%99%D7%A6%D7%97%D7%A7_%D7%92%D7%99%D7%A0%D7%96%D7%91%D7%95%D7%A8%D7%92_(%D7%A4%D7%99%D7%A8%D7%95%D7%A9%D7%95%D7%A0%D7%99%D7%9D)\" class=\"mw-disambig\" title=\"יצחק גינזבורג (פירושונים)\">יצחק גינזבורג (פירושונים)</a></span>.</div>\n<figure class=\"mw-default-size\" typeof=\"mw:File/Thumb\"><a href=\"/index.php/%D7%A7%D7%95%D7%91%D7%A5:Ganzburg,_Itchke_05.jpg\" class=\"mw-file-description\"><img src=\"/images/thumb/a/ae/Ganzburg%2C_Itchke_05.jpg/220px-Ganzburg%2C_Itchke_05.jpg\" decoding=\"async\" width=\"220\" height=\"327\" class=\"mw-file-element\" srcset=\"/images/thumb/a/ae/Ganzburg%2C_Itchke_05.jpg/330px-Ganzburg%2C_Itchke_05.jpg 1.5x, /images/thumb/a/ae/Ganzburg%2C_Itchke_05.jpg/440px-Ganzburg%2C_Itchke_05.jpg 2x\" /></a><figcaption>ר' יצחק גנזבורג</figcaption></figure>\n<p>הרב <b>יצחק (איצ'קה) גאנזבורג</b> (<a href=\"/index.php/%D7%99%22%D7%91_%D7%AA%D7%9E%D7%95%D7%96\" class=\"mw-redirect\" title=\"י&quot;ב תמוז\">י\"ב תמוז</a> <a href=\"/index.php/%D7%AA%D7%A8%D7%A4%22%D7%96\" title=\"תרפ&quot;ז\">תרפ\"ז</a>, 1927 - <a href=\"/index.php/%D7%99%22%D7%93_%D7%90%D7%93%D7%A8\" class=\"mw-redirect\" title=\"י&quot;ד אדר\">י\"ד אדר</a> <a href=\"/index.php/%D7%AA%D7%A9%D7%A1%22%D7%95\" title=\"תשס&quot;ו\">תשס\"ו</a>, 2006) היה מפעילי <a href=\"/index.php/%D7%A6%D7%A2%D7%99%D7%A8%D7%99_%D7%90%D7%92%D7%95%D7%93%D7%AA_%D7%97%D7%91%22%D7%93\" title=\"צעירי אגודת חב&quot;ד\">צעירי אגודת חב\"ד</a> בשנות היו\"דים והכ\"פים, וחבר הנהלת <a href=\"/index.php/%D7%A8%D7%A9%D7%AA_%D7%90%D7%94%D7%9C%D7%99_%D7%99%D7%95%D7%A1%D7%A3_%D7%99%D7%A6%D7%97%D7%A7_%D7%91%D7%90%D7%A8%D7%A5_%D7%94%D7%A7%D7%95%D7%93%D7%A9\" class=\"mw-redirect\" title=\"רשת אהלי יוסף יצחק בארץ הקודש\">רשת אהלי יוסף יצחק בארץ הקודש</a> באותם שנים. בשנת <a href=\"/index.php/%D7%AA%D7%A9%D7%99%22%D7%92\" title=\"תשי&quot;ג\">תשי\"ג</a> הצטרף ל<a href=\"/index.php/%D7%90%D7%92%D7%95%D7%93%D7%AA_%D7%97%D7%A1%D7%99%D7%93%D7%99_%D7%97%D7%91%22%D7%93_%D7%91%D7%90%D7%A8%D7%A5_%D7%94%D7%A7%D7%95%D7%93%D7%A9\" class=\"mw-redirect\" title=\"אגודת חסידי חב&quot;ד בארץ הקודש\">אגודת חסידי חב\"ד בארץ הקודש</a>.\n</p><p>הרב איצ'קה יזם את <a href=\"/index.php/%D7%9E%D7%91%D7%A6%D7%A2_%D7%9E%D7%A6%D7%94_%D7%9C%D7%AA%D7%9C%D7%9E%D7%99%D7%93\" title=\"מבצע מצה לתלמיד\">מבצע מצה לתלמיד</a> של <a href=\"/index.php/%D7%A6%D7%A2%D7%99%D7%A8%D7%99_%D7%90%D7%92%D7%95%D7%93%D7%AA_%D7%97%D7%91%22%D7%93_%D7%91%D7%99%D7%A9%D7%A8%D7%90%D7%9C\" title=\"צעירי אגודת חב&quot;ד בישראל\">צעירי אגודת חב\"ד</a>.\n</p>\n<figure class=\"mw-halign-left\" typeof=\"mw:File/Thumb\"><a href=\"/index.php/%D7%A7%D7%95%D7%91%D7%A5:%D7%99%D7%A6%D7%97%D7%A7_%D7%92%D7%A0%D7%96%D7%91%D7%95%D7%A8%D7%92.jpg\" class=\"mw-file-description\"><img src=\"/images/thumb/3/38/%D7%99%D7%A6%D7%97%D7%A7_%D7%92%D7%A0%D7%96%D7%91%D7%95%D7%A8%D7%92.jpg/250px-%D7%99%D7%A6%D7%97%D7%A7_%D7%92%D7%A0%D7%96%D7%91%D7%95%D7%A8%D7%92.jpg\" decoding=\"async\" width=\"250\" height=\"178\" class=\"mw-file-element\" srcset=\"/images/thumb/3/38/%D7%99%D7%A6%D7%97%D7%A7_%D7%92%D7%A0%D7%96%D7%91%D7%95%D7%A8%D7%92.jpg/375px-%D7%99%D7%A6%D7%97%D7%A7_%D7%92%D7%A0%D7%96%D7%91%D7%95%D7%A8%D7%92.jpg 1.5x, /images/3/38/%D7%99%D7%A6%D7%97%D7%A7_%D7%92%D7%A0%D7%96%D7%91%D7%95%D7%A8%D7%92.jpg 2x\" /></a><figcaption>הרב גנזבורג מקבל <a href=\"/index.php/%D7%9C%D7%A2%D7%A7%D7%90%D7%97\" title=\"לעקאח\">לעקאח</a> מהרבי</figcaption></figure>\n<meta property=\"mw:PageProp/toc\" />\n<h2><span id=\".D7.AA.D7.95.D7.9C.D7.93.D7.95.D7.AA_.D7.97.D7.99.D7.99.D7.9D\"></span><span class=\"mw-headline\" id=\"תולדות_חיים\">תולדות חיים</span><span class=\"mw-editsection\"><span class=\"mw-editsection-bracket\">[</span><a href=\"/index.php?title=%D7%99%D7%A6%D7%97%D7%A7_%D7%92%D7%A0%D7%96%D7%91%D7%95%D7%A8%D7%92&amp;veaction=edit&amp;section=1\" title=\"עריכת פסקה: &quot;תולדות חיים&quot;\" class=\"mw-editsection-visualeditor\"><span>עריכה</span></a><span class=\"mw-editsection-divider\"> | </span><a href=\"/index.php?title=%D7%99%D7%A6%D7%97%D7%A7_%D7%92%D7%A0%D7%96%D7%91%D7%95%D7%A8%D7%92&amp;action=edit&amp;section=1\" title=\"עריכת קוד המקור של הפרק: תולדות חיים\"><span>עריכת קוד מקור</span></a><span class=\"mw-editsection-bracket\">]</span></span></h2>\n<p>נולד ב<a href=\"/index.php/%D7%98%22%D7%95_%D7%AA%D7%9E%D7%95%D7%96\" class=\"mw-redirect\" title=\"ט&quot;ו תמוז\">ט\"ו תמוז</a> <a href=\"/index.php/%D7%AA%D7%A8%D7%A4%22%D7%96\" title=\"תרפ&quot;ז\">תרפ\"ז</a> לאביו הרב <a href=\"/index.php/%D7%9E%D7%A9%D7%94_%D7%93%D7%95%D7%91%D7%A2%D7%A8_%D7%92%D7%A0%D7%96%D7%91%D7%95%D7%A8%D7%92\" title=\"משה דובער גנזבורג\">משה דובער גנזבורג</a> ולאמו מרת דובא ב<a href=\"/index.php/%D7%9E%D7%95%D7%A1%D7%A7%D7%91%D7%94\" title=\"מוסקבה\">מוסקבה</a>.\n</p><p>עוד קודם פרוץ <a href=\"/index.php/%D7%9E%D7%9C%D7%97%D7%9E%D7%AA_%D7%94%D7%A2%D7%95%D7%9C%D7%9D_%D7%94%D7%A9%D7%A0%D7%99%D7%99%D7%94\" title=\"מלחמת העולם השנייה\">מלחמת העולם השנייה</a> ב<a href=\"/index.php/%D7%9B%27_%D7%9B%D7%A1%D7%9C%D7%95\" class=\"mw-redirect\" title=\"כ&#39; כסלו\">כ' כסלו</a> <a href=\"/index.php/%D7%AA%D7%A8%D7%A6%22%D7%97\" class=\"mw-redirect\" title=\"תרצ&quot;ח\">תרצ\"ח</a>, עלה יחד עם משפחתו ל<a href=\"/index.php/%D7%90%D7%A8%D7%A5_%D7%94%D7%A7%D7%95%D7%93%D7%A9\" class=\"mw-redirect\" title=\"ארץ הקודש\">ארץ הקודש</a> והיה מתלמידיה הראשונים של ישיבת <a href=\"/index.php/%D7%90%D7%97%D7%99_%D7%AA%D7%9E%D7%99%D7%9E%D7%99%D7%9D_%D7%AA%D7%9C_%D7%90%D7%91%D7%99%D7%91\" title=\"אחי תמימים תל אביב\">אחי תמימים תל אביב</a>.\n</p><p>ב<a href=\"/index.php/%D7%91%27_%D7%A0%D7%99%D7%A1%D7%9F\" class=\"mw-redirect\" title=\"ב&#39; ניסן\">ב' ניסן</a> <a href=\"/index.php/%D7%AA%D7%A9%22%D7%99\" title=\"תש&quot;י\">תש\"י</a> התחתן עם גיטה, בת החסיד הרב <a href=\"/index.php/%D7%A8%D7%A4%D7%90%D7%9C_%D7%A0%D7%97%D7%9E%D7%9F_%D7%9B%D7%94%D7%9F\" title=\"רפאל נחמן כהן\">רפאל נחמן כהן</a>.\n</p><p>בשנת <a href=\"/index.php/%D7%AA%D7%A9%D7%9C%22%D7%95\" title=\"תשל&quot;ו\">תשל\"ו</a> היגר ל<a href=\"/index.php/%D7%90%D7%A8%D7%A6%D7%95%D7%AA_%D7%94%D7%91%D7%A8%D7%99%D7%AA\" title=\"ארצות הברית\">ארצות הברית</a> וקבע את מגוריו בשכונת <a href=\"/index.php/%D7%A7%D7%A8%D7%90%D7%95%D7%9F_%D7%94%D7%99%D7%99%D7%98%D7%A1\" title=\"קראון הייטס\">קראון הייטס</a> בסמיכות לחצר הרבי ב-<a href=\"/index.php/770\" class=\"mw-redirect\" title=\"770\">770</a>.\n</p><p>בשנת <a href=\"/index.php/%D7%AA%D7%A9%D7%9E%22%D7%98\" title=\"תשמ&quot;ט\">תשמ\"ט</a> קיבל מ<a href=\"/index.php/%D7%94%D7%A8%D7%91%D7%99\" class=\"mw-redirect\" title=\"הרבי\">הרבי</a> הוראה להתעסק עם הוצאתו לאור של <a href=\"/index.php/%D7%A1%D7%A4%D7%A8_%D7%94%D7%AA%D7%9E%D7%99%D7%9E%D7%99%D7%9D\" title=\"ספר התמימים\">ספר התמימים</a>, וזכה לעסוק בעצמו בהוצאתם לאור של שני החלקים הראשונים<sup id=\"cite_ref-1\" class=\"reference\"><a href=\"#cite_note-1\"><span class=\"cite-bracket\">&#91;</span>1<span class=\"cite-bracket\">&#93;</span></a></sup>. החלק השלישי יצא לאור בשנותיו האחרונות, ומכיון שהוא הרגיש שאין בכוחו לעסוק בזה בעצמו, ביקש מהנהלת <a href=\"/index.php/%D7%90%D7%99%D7%92%D7%95%D7%93_%D7%AA%D7%9C%D7%9E%D7%99%D7%93%D7%99_%D7%94%D7%99%D7%A9%D7%99%D7%91%D7%95%D7%AA_%D7%94%D7%A2%D7%95%D7%9C%D7%9E%D7%99\" class=\"mw-redirect\" title=\"איגוד תלמידי הישיבות העולמי\">איגוד תלמידי הישיבות העולמי</a> לסייע לו בעבודת האיסוף וההוצאה לאור.\n</p><p>הרב גאנזבורג היה שותף פעיל ב<a href=\"/index.php/%D7%A2%D7%A8%D7%91_%D7%97%D7%91%22%D7%93\" title=\"ערב חב&quot;ד\">ערבי חב\"ד</a> שאורגנו במושבים ובקיבוצים על ידי <a href=\"/index.php/%D7%A6%D7%90%22%D7%97\" class=\"mw-redirect\" title=\"צא&quot;ח\">צא\"ח</a> ופעיל נמרץ ב<a href=\"/index.php/%D7%A4%D7%A8%D7%A1%D7%95%D7%9D_%D7%91%D7%A9%D7%95%D7%A8%D7%AA_%D7%94%D7%92%D7%90%D7%95%D7%9C%D7%94\" class=\"mw-redirect\" title=\"פרסום בשורת הגאולה\">פרסום בשורת הגאולה</a> <a href=\"/index.php/%D7%94%D7%A8%D7%91%D7%99_%D7%9E%D7%9C%D7%99%D7%95%D7%91%D7%90%D7%95%D7%95%D7%99%D7%98%D7%A9_%D7%9B%D7%9E%D7%9C%D7%9A_%D7%94%D7%9E%D7%A9%D7%99%D7%97\" title=\"הרבי מליובאוויטש כמלך המשיח\">והגואל</a> בכל שכבות הציבור. יוזמה ייחודית שלו הייתה הפצת בקבוקוני \"המים של <a href=\"/index.php/%D7%94%D7%A8%D7%91%D7%99\" class=\"mw-redirect\" title=\"הרבי\">הרבי</a>\" בקרב לא-יהודים ביחד עם פרסום על <a href=\"/index.php/%D7%A9%D7%91%D7%A2_%D7%9E%D7%A6%D7%95%D7%95%D7%AA_%D7%91%D7%A0%D7%99_%D7%A0%D7%97\" title=\"שבע מצוות בני נח\">שבע מצוות בני נח</a>. כמו כן יזם את גימיק השלכת הכרוזים ממטוסים בחג ה<a href=\"/index.php/%D7%A4%D7%95%D7%A8%D7%99%D7%9D\" title=\"פורים\">פורים</a> בשנות הכ\"פים ובשנת <a href=\"/index.php/%D7%AA%D7%A9%D7%A0%22%D7%91\" title=\"תשנ&quot;ב\">תשנ\"ב</a> השתמש ברעיון זה בהשלכת כרוזים אודות <a href=\"/index.php/%D7%9E%D7%A9%D7%99%D7%97\" class=\"mw-redirect\" title=\"משיח\">משיח</a> כשהדבר נעשה בברכת <a href=\"/index.php/%D7%94%D7%A8%D7%91%D7%99\" class=\"mw-redirect\" title=\"הרבי\">הרבי</a>.\n</p><p>\nגם אחרי <a href=\"/index.php/%D7%92%27_%D7%AA%D7%9E%D7%95%D7%96_%D7%AA%D7%A9%D7%A0%22%D7%93\" class=\"mw-redirect\" title=\"ג&#39; תמוז תשנ&quot;ד\">ג' תמוז</a> המשיך בפירסום האמונה הטהורה ב<a href=\"/index.php/%D7%A0%D7%A6%D7%97%D7%99%D7%95%D7%AA_%D7%97%D7%99%D7%99%D7%95_%D7%A9%D7%9C_%D7%94%D7%A8%D7%91%D7%99\" title=\"נצחיות חייו של הרבי\">נצחיות חייו של הרבי שליט\"א</a> והתגשמות <a href=\"/index.php/%D7%94%D7%A8%D7%91%D7%99_%D7%9B%D7%9E%D7%9C%D7%9A_%D7%94%D7%9E%D7%A9%D7%99%D7%97\" class=\"mw-redirect\" title=\"הרבי כמלך המשיח\">נבואת הגאולה</a>, ואף השתתף ב<a href=\"/index.php/%D7%9B%D7%99%D7%A0%D7%95%D7%A1%D7%99_%D7%92%D7%90%D7%95%D7%9C%D7%94_%D7%95%D7%9E%D7%A9%D7%99%D7%97_-_%D7%AA%D7%A9%D7%A0%22%D7%94\" title=\"כינוסי גאולה ומשיח - תשנ&quot;ה\">כינוסי גאולה ומשיח</a> שהתקיימו בשנת <a href=\"/index.php/%D7%AA%D7%A9%D7%A0%22%D7%94\" title=\"תשנ&quot;ה\">תשנ\"ה</a> על ידי הרב <a href=\"/index.php/%D7%96%D7%9E%D7%A8%D7%95%D7%A0%D7%99_%D7%A6%D7%99%D7%A7\" class=\"mw-redirect\" title=\"זמרוני ציק\">זמרוני ציק</a> ונאם בכינסי פעילים שקדמו לאירוע.</p><figure class=\"mw-halign-left\" typeof=\"mw:File/Thumb\"><a href=\"/index.php/%D7%A7%D7%95%D7%91%D7%A5:%D7%97%D7%99%D7%99%D7%9C_%D7%91%D7%A9%D7%99%D7%A8%D7%95%D7%AA_%D7%94%D7%A8%D7%91%D7%99.jpg\" class=\"mw-file-description\"><img src=\"/images/thumb/8/86/%D7%97%D7%99%D7%99%D7%9C_%D7%91%D7%A9%D7%99%D7%A8%D7%95%D7%AA_%D7%94%D7%A8%D7%91%D7%99.jpg/100px-%D7%97%D7%99%D7%99%D7%9C_%D7%91%D7%A9%D7%99%D7%A8%D7%95%D7%AA_%D7%94%D7%A8%D7%91%D7%99.jpg\" decoding=\"async\" width=\"100\" height=\"148\" class=\"mw-file-element\" srcset=\"/images/thumb/8/86/%D7%97%D7%99%D7%99%D7%9C_%D7%91%D7%A9%D7%99%D7%A8%D7%95%D7%AA_%D7%94%D7%A8%D7%91%D7%99.jpg/150px-%D7%97%D7%99%D7%99%D7%9C_%D7%91%D7%A9%D7%99%D7%A8%D7%95%D7%AA_%D7%94%D7%A8%D7%91%D7%99.jpg 1.5x, /images/thumb/8/86/%D7%97%D7%99%D7%99%D7%9C_%D7%91%D7%A9%D7%99%D7%A8%D7%95%D7%AA_%D7%94%D7%A8%D7%91%D7%99.jpg/200px-%D7%97%D7%99%D7%99%D7%9C_%D7%91%D7%A9%D7%99%D7%A8%D7%95%D7%AA_%D7%94%D7%A8%D7%91%D7%99.jpg 2x\" /></a><figcaption>כריכת הספר</figcaption></figure><p>ב<a href=\"/index.php/%D7%99%22%D7%93_%D7%90%D7%93%D7%A8\" class=\"mw-redirect\" title=\"י&quot;ד אדר\">תענית אסתר</a> <a href=\"/index.php/%D7%AA%D7%A9%D7%A1%22%D7%95\" title=\"תשס&quot;ו\">תשס\"ו</a> נפטר, ונטמן בחלקת חב\"ד בבית העלמין מונטיפיורי, ברובע קווינס שבניו יורק.\n</p><p>את זכרונותיו פרסם ב<a href=\"/index.php/%D7%A9%D7%91%D7%95%D7%A2%D7%95%D7%9F_%D7%91%D7%99%D7%AA_%D7%9E%D7%A9%D7%99%D7%97\" class=\"mw-redirect\" title=\"שבועון בית משיח\">שבועון בית משיח</a>, ונדפסו אחר כך בספר \"<a href=\"/index.php/%D7%97%D7%99%D7%99%D7%9C_%D7%91%D7%A9%D7%99%D7%A8%D7%95%D7%AA_%D7%94%D7%A8%D7%91%D7%99\" class=\"mw-redirect\" title=\"חייל בשירות הרבי\">חייל בשירות הרבי</a>\".\n</p>\n<h2><span id=\".D7.94.D7.A1.D7.A4.D7.A8_.D7.97.D7.99.D7.99.D7.9C_.D7.91.D7.A9.D7.99.D7.A8.D7.95.D7.AA_.D7.94.D7.A8.D7.91.D7.99\"></span><span class=\"mw-headline\" id=\"הספר_חייל_בשירות_הרבי\">הספר חייל בשירות הרבי</span><span class=\"mw-editsection\"><span class=\"mw-editsection-bracket\">[</span><a href=\"/index.php?title=%D7%99%D7%A6%D7%97%D7%A7_%D7%92%D7%A0%D7%96%D7%91%D7%95%D7%A8%D7%92&amp;veaction=edit&amp;section=2\" title=\"עריכת פסקה: &quot;הספר חייל בשירות הרבי&quot;\" class=\"mw-editsection-visualeditor\"><span>עריכה</span></a><span class=\"mw-editsection-divider\"> | </span><a href=\"/index.php?title=%D7%99%D7%A6%D7%97%D7%A7_%D7%92%D7%A0%D7%96%D7%91%D7%95%D7%A8%D7%92&amp;action=edit&amp;section=2\" title=\"עריכת קוד המקור של הפרק: הספר חייל בשירות הרבי\"><span>עריכת קוד מקור</span></a><span class=\"mw-editsection-bracket\">]</span></span></h2><p>\nבשנת <a href=\"/index.php/%D7%AA%D7%A9%D7%A0%22%D7%98\" title=\"תשנ&quot;ט\">תשנ\"ט</a> יצא לאור הספר <b>חייל בשירות הרבי</b> הכולל את זכרונותיו של הרב יצחק גנזבורג מהשנים <a href=\"/index.php/%D7%AA%D7%A8%D7%A4%22%D7%96\" title=\"תרפ&quot;ז\">תרפ\"ז</a> - <a href=\"/index.php/%D7%AA%D7%A9%D7%9B%22%D7%93\" title=\"תשכ&quot;ד\">תשכ\"ד</a>, כולל: ילדותו ב<a href=\"/index.php/%D7%A8%D7%95%D7%A1%D7%99%D7%94\" title=\"רוסיה\">רוסיה</a>; לימודיו בישיבת <a href=\"/index.php/%D7%90%D7%97%D7%99_%D7%AA%D7%9E%D7%99%D7%9E%D7%99%D7%9D_%D7%AA%D7%9C_%D7%90%D7%91%D7%99%D7%91\" title=\"אחי תמימים תל אביב\">אחי תמימים תל אביב</a> אצל ר' <a href=\"/index.php/%D7%A9%D7%90%D7%95%D7%9C_%D7%91%D7%A8%D7%95%D7%A7\" class=\"mw-redirect\" title=\"שאול ברוק\">שאול ברוק</a>; שירותו ה<a href=\"/index.php/%D7%A6%D7%94%22%D7%9C\" title=\"צה&quot;ל\">צבאי</a>; ראשית פעולותיו ב<a href=\"/index.php/%D7%90%D7%A8%D7%A5_%D7%94%D7%A7%D7%95%D7%93%D7%A9\" class=\"mw-redirect\" title=\"ארץ הקודש\">ארץ הקודש</a> ו<a href=\"/index.php/%D7%90%D7%92%D7%A8%D7%95%D7%AA_%D7%A7%D7%95%D7%93%D7%A9\" class=\"mw-redirect\" title=\"אגרות קודש\">מכתבי</a> <a href=\"/index.php/%D7%94%D7%A8%D7%91%D7%99\" class=\"mw-redirect\" title=\"הרבי\">הרבי</a> אליו. הזכרונות נרשמו על ידי הרב <a href=\"/index.php/%D7%90%D7%91%D7%A8%D7%94%D7%9D_%D7%99%D7%A9%D7%A2%D7%99%D7%94_%D7%A8%D7%99%D7%99%D7%A0%D7%99%D7%A5\" title=\"אברהם ישעיה רייניץ\">אברהם רייניץ</a>, ופורסמו בהמשכים ב<a href=\"/index.php/%D7%A9%D7%91%D7%95%D7%A2%D7%95%D7%9F_%D7%91%D7%99%D7%AA_%D7%9E%D7%A9%D7%99%D7%97\" class=\"mw-redirect\" title=\"שבועון בית משיח\">שבועון בית משיח</a> קודם שיצאו לאור כספר.</p><figure class=\"mw-default-size\" typeof=\"mw:File/Thumb\"><a href=\"/index.php/%D7%A7%D7%95%D7%91%D7%A5:%D7%94%D7%90%D7%97%D7%99%D7%9D_%D7%94%D7%99%D7%99%D7%A9%D7%A7%D7%A2,_%D7%9C%D7%99%D7%99%D7%91%D7%9C_%D7%95%D7%90%D7%99%D7%A6%27%D7%A7%D7%A2.jpg\" class=\"mw-file-description\"><img src=\"/images/thumb/4/44/%D7%94%D7%90%D7%97%D7%99%D7%9D_%D7%94%D7%99%D7%99%D7%A9%D7%A7%D7%A2%2C_%D7%9C%D7%99%D7%99%D7%91%D7%9C_%D7%95%D7%90%D7%99%D7%A6%27%D7%A7%D7%A2.jpg/220px-%D7%94%D7%90%D7%97%D7%99%D7%9D_%D7%94%D7%99%D7%99%D7%A9%D7%A7%D7%A2%2C_%D7%9C%D7%99%D7%99%D7%91%D7%9C_%D7%95%D7%90%D7%99%D7%A6%27%D7%A7%D7%A2.jpg\" decoding=\"async\" width=\"220\" height=\"140\" class=\"mw-file-element\" srcset=\"/images/thumb/4/44/%D7%94%D7%90%D7%97%D7%99%D7%9D_%D7%94%D7%99%D7%99%D7%A9%D7%A7%D7%A2%2C_%D7%9C%D7%99%D7%99%D7%91%D7%9C_%D7%95%D7%90%D7%99%D7%A6%27%D7%A7%D7%A2.jpg/330px-%D7%94%D7%90%D7%97%D7%99%D7%9D_%D7%94%D7%99%D7%99%D7%A9%D7%A7%D7%A2%2C_%D7%9C%D7%99%D7%99%D7%91%D7%9C_%D7%95%D7%90%D7%99%D7%A6%27%D7%A7%D7%A2.jpg 1.5x, /images/thumb/4/44/%D7%94%D7%90%D7%97%D7%99%D7%9D_%D7%94%D7%99%D7%99%D7%A9%D7%A7%D7%A2%2C_%D7%9C%D7%99%D7%99%D7%91%D7%9C_%D7%95%D7%90%D7%99%D7%A6%27%D7%A7%D7%A2.jpg/440px-%D7%94%D7%90%D7%97%D7%99%D7%9D_%D7%94%D7%99%D7%99%D7%A9%D7%A7%D7%A2%2C_%D7%9C%D7%99%D7%99%D7%91%D7%9C_%D7%95%D7%90%D7%99%D7%A6%27%D7%A7%D7%A2.jpg 2x\" /></a><figcaption>הרב יצחק גנזבורג בשמאל התמונה, עם אחיו <a href=\"/index.php/%D7%A9%D7%9C%D7%95%D7%9D_%D7%99%D7%94%D7%95%D7%93%D7%94_%D7%9C%D7%99%D7%99%D7%91_%D7%92%D7%99%D7%A0%D7%96%D7%91%D7%95%D7%A8%D7%92\" title=\"שלום יהודה לייב גינזבורג\">לייבל</a> ו<a href=\"/index.php/%D7%A6%D7%91%D7%99_%D7%94%D7%99%D7%A8%D7%A9_%D7%92%D7%A0%D7%96%D7%91%D7%95%D7%A8%D7%92\" title=\"צבי הירש גנזבורג\">היישקע</a></figcaption></figure>\n<h2><span id=\".D7.9E.D7.A9.D7.A4.D7.97.D7.AA.D7.95\"></span><span class=\"mw-headline\" id=\"משפחתו\">משפחתו</span><span class=\"mw-editsection\"><span class=\"mw-editsection-bracket\">[</span><a href=\"/index.php?title=%D7%99%D7%A6%D7%97%D7%A7_%D7%92%D7%A0%D7%96%D7%91%D7%95%D7%A8%D7%92&amp;veaction=edit&amp;section=3\" title=\"עריכת פסקה: &quot;משפחתו&quot;\" class=\"mw-editsection-visualeditor\"><span>עריכה</span></a><span class=\"mw-editsection-divider\"> | </span><a href=\"/index.php?title=%D7%99%D7%A6%D7%97%D7%A7_%D7%92%D7%A0%D7%96%D7%91%D7%95%D7%A8%D7%92&amp;action=edit&amp;section=3\" title=\"עריכת קוד המקור של הפרק: משפחתו\"><span>עריכת קוד מקור</span></a><span class=\"mw-editsection-bracket\">]</span></span></h2>\n<ul><li><b>אביו</b>: הרב <a href=\"/index.php/%D7%9E%D7%A9%D7%94_%D7%93%D7%95%D7%91%D7%A2%D7%A8_%D7%92%D7%A0%D7%96%D7%91%D7%95%D7%A8%D7%92\" title=\"משה דובער גנזבורג\">משה דובער גנזבורג</a> - חבר הנהלת <a href=\"/index.php/%D7%90%D7%92%D7%95%D7%93%D7%AA_%D7%97%D7%A1%D7%99%D7%93%D7%99_%D7%97%D7%91%22%D7%93_%D7%91%D7%90%D7%94%22%D7%A7\" class=\"mw-redirect\" title=\"אגודת חסידי חב&quot;ד באה&quot;ק\">אגודת חסידי חב\"ד באה\"ק</a>.</li>\n<li><b>אמו</b>: מרת דובא (לבית דוטליבוב) נכדת האחים שפירא וצאצאית של ר' פנחס מקוריץ</li>\n<li><b>חמיו</b>: הרב <a href=\"/index.php/%D7%A8%D7%A4%D7%90%D7%9C_%D7%A0%D7%97%D7%9E%D7%9F_%D7%9B%D7%94%D7%9F\" title=\"רפאל נחמן כהן\">רפאל נחמן כהן</a> - מחבר הספר <a href=\"/index.php/%D7%A9%D7%9E%D7%95%D7%A2%D7%95%D7%AA_%D7%95%D7%A1%D7%99%D7%A4%D7%95%D7%A8%D7%99%D7%9D\" title=\"שמועות וסיפורים\">שמועות וסיפורים</a>.</li>\n<li><b>רעייתו</b>: גב' <a href=\"/index.php?title=%D7%92%D7%99%D7%98%D7%9C_%D7%92%D7%A0%D7%96%D7%91%D7%95%D7%A8%D7%92&amp;action=edit&amp;redlink=1\" class=\"new\" title=\"גיטל גנזבורג (הדף אינו קיים)\">גיטל גנזבורג</a> - נפטרה ו כסלו תשע\"ה.</li>\n<li><b>בנו</b>: הרב <a href=\"/index.php?title=%D7%99%D7%95%D7%A1%D7%A3_%D7%92%D7%90%D7%A0%D7%96%D7%91%D7%95%D7%A8%D7%92&amp;action=edit&amp;redlink=1\" class=\"new\" title=\"יוסף גאנזבורג (הדף אינו קיים)\">יוסף גאנזבורג</a>, <a href=\"/index.php/%D7%A7%D7%A0%D7%93%D7%94\" title=\"קנדה\">קנדה</a>.</li>\n<li><b>חתנו</b>: הרב <a href=\"/index.php/%D7%A9%D7%A0%D7%99%D7%90%D7%95%D7%A8_%D7%96%D7%9C%D7%9E%D7%9F_%D7%99%D7%A6%D7%97%D7%A7_%D7%99%D7%94%D7%95%D7%A9%D7%A2_%D7%97%D7%90%D7%A0%D7%99%D7%9F\" class=\"mw-redirect\" title=\"שניאור זלמן יצחק יהושע חאנין\">שניאור זלמן יצחק יהושע חאנין</a> - מנהל <a href=\"/index.php/%D7%95%D7%A2%D7%93_%D7%9C%D7%94%D7%A4%D7%A6%D7%AA_%D7%A9%D7%99%D7%97%D7%95%D7%AA\" title=\"ועד להפצת שיחות\">ועד להפצת שיחות</a>, <a href=\"/index.php/%D7%A7%D7%A8%D7%90%D7%95%D7%9F_%D7%94%D7%99%D7%99%D7%98%D7%A1\" title=\"קראון הייטס\">קראון הייטס</a>.</li>\n<li><b>חתנו</b>: הרב <a href=\"/index.php/%D7%99%D7%A9%D7%A8%D7%90%D7%9C_%D7%91%D7%A8%D7%95%D7%93\" title=\"ישראל ברוד\">ישראל ברוד</a> - <a href=\"/index.php/%D7%9B%D7%A4%D7%A8_%D7%97%D7%91%22%D7%93\" title=\"כפר חב&quot;ד\">כפר חב\"ד</a>.</li>\n<li><b>גיסו</b>: ה'חוזר' <a href=\"/index.php/%D7%99%D7%95%D7%90%D7%9C_%D7%9B%D7%94%D7%9F\" title=\"יואל כהן\">יואל כהן</a></li></ul>\n<h2><span id=\".D7.A7.D7.99.D7.A9.D7.95.D7.A8.D7.99.D7.9D_.D7.97.D7.99.D7.A6.D7.95.D7.A0.D7.99.D7.99.D7.9D\"></span><span class=\"mw-headline\" id=\"קישורים_חיצוניים\">קישורים חיצוניים</span><span class=\"mw-editsection\"><span class=\"mw-editsection-bracket\">[</span><a href=\"/index.php?title=%D7%99%D7%A6%D7%97%D7%A7_%D7%92%D7%A0%D7%96%D7%91%D7%95%D7%A8%D7%92&amp;veaction=edit&amp;section=4\" title=\"עריכת פסקה: &quot;קישורים חיצוניים&quot;\" class=\"mw-editsection-visualeditor\"><span>עריכה</span></a><span class=\"mw-editsection-divider\"> | </span><a href=\"/index.php?title=%D7%99%D7%A6%D7%97%D7%A7_%D7%92%D7%A0%D7%96%D7%91%D7%95%D7%A8%D7%92&amp;action=edit&amp;section=4\" title=\"עריכת קוד המקור של הפרק: קישורים חיצוניים\"><span>עריכת קוד מקור</span></a><span class=\"mw-editsection-bracket\">]</span></span></h2>\n<ul><li><a href=\"/index.php/%D7%90%D7%91%D7%A8%D7%94%D7%9D_%D7%A8%D7%99%D7%99%D7%A0%D7%99%D7%A5\" class=\"mw-redirect\" title=\"אברהם רייניץ\">אברהם רייניץ</a>, <b><a rel=\"nofollow\" class=\"external text\" href=\"http://www.beismoshiach.org/Lashon_HaKodesh/pdf/548.pdf\">חייל בשירות הרבי</a></b>, סקירה מקוצרת של תולדות חייו ופעולותיו, <a href=\"/index.php/%D7%A9%D7%91%D7%95%D7%A2%D7%95%D7%9F_%D7%91%D7%99%D7%AA_%D7%9E%D7%A9%D7%99%D7%97\" class=\"mw-redirect\" title=\"שבועון בית משיח\">שבועון בית משיח</a>, גליון 548 עמוד 32.</li>\n<li><a rel=\"nofollow\" class=\"external text\" href=\"http://www.video.hageula.com/musicvideo.php?vid=2266839d0\">נאומו בכינוס הפעילים שבט תשנ\"ה</a> במסגרת פעילות <a href=\"/index.php/%D7%94%D7%90%D7%92%D7%95%D7%93%D7%94_%D7%9C%D7%9E%D7%A2%D7%9F_%D7%94%D7%92%D7%90%D7%95%D7%9C%D7%94\" class=\"mw-redirect\" title=\"האגודה למען הגאולה\">האגודה למען הגאולה</a> <span typeof=\"mw:File\"><span><img src=\"/images/thumb/d/d6/%D7%A1%D7%9E%D7%9C_%D7%95%D7%99%D7%93%D7%99%D7%90%D7%95_%D7%9E%D7%97%D7%95%D7%93%D7%A9_5.svg/16px-%D7%A1%D7%9E%D7%9C_%D7%95%D7%99%D7%93%D7%99%D7%90%D7%95_%D7%9E%D7%97%D7%95%D7%93%D7%A9_5.svg.png\" decoding=\"async\" width=\"16\" height=\"11\" class=\"mw-file-element\" srcset=\"/images/thumb/d/d6/%D7%A1%D7%9E%D7%9C_%D7%95%D7%99%D7%93%D7%99%D7%90%D7%95_%D7%9E%D7%97%D7%95%D7%93%D7%A9_5.svg/24px-%D7%A1%D7%9E%D7%9C_%D7%95%D7%99%D7%93%D7%99%D7%90%D7%95_%D7%9E%D7%97%D7%95%D7%93%D7%A9_5.svg.png 1.5x, /images/thumb/d/d6/%D7%A1%D7%9E%D7%9C_%D7%95%D7%99%D7%93%D7%99%D7%90%D7%95_%D7%9E%D7%97%D7%95%D7%93%D7%A9_5.svg/32px-%D7%A1%D7%9E%D7%9C_%D7%95%D7%99%D7%93%D7%99%D7%90%D7%95_%D7%9E%D7%97%D7%95%D7%93%D7%A9_5.svg.png 2x\" /></span></span></li>\n<li><b><a rel=\"nofollow\" class=\"external text\" href=\"https://col.org.il/news/129432\">החסיד יזם טיסת אווירון שתעורר על מבצע פורים. איך הגיב הרבי?</a></b> <span typeof=\"mw:File\"><span><img src=\"/images/thumb/d/d6/%D7%A1%D7%9E%D7%9C_%D7%95%D7%99%D7%93%D7%99%D7%90%D7%95_%D7%9E%D7%97%D7%95%D7%93%D7%A9_5.svg/16px-%D7%A1%D7%9E%D7%9C_%D7%95%D7%99%D7%93%D7%99%D7%90%D7%95_%D7%9E%D7%97%D7%95%D7%93%D7%A9_5.svg.png\" decoding=\"async\" width=\"16\" height=\"11\" class=\"mw-file-element\" srcset=\"/images/thumb/d/d6/%D7%A1%D7%9E%D7%9C_%D7%95%D7%99%D7%93%D7%99%D7%90%D7%95_%D7%9E%D7%97%D7%95%D7%93%D7%A9_5.svg/24px-%D7%A1%D7%9E%D7%9C_%D7%95%D7%99%D7%93%D7%99%D7%90%D7%95_%D7%9E%D7%97%D7%95%D7%93%D7%A9_5.svg.png 1.5x, /images/thumb/d/d6/%D7%A1%D7%9E%D7%9C_%D7%95%D7%99%D7%93%D7%99%D7%90%D7%95_%D7%9E%D7%97%D7%95%D7%93%D7%A9_5.svg/32px-%D7%A1%D7%9E%D7%9C_%D7%95%D7%99%D7%93%D7%99%D7%90%D7%95_%D7%9E%D7%97%D7%95%D7%93%D7%A9_5.svg.png 2x\" /></span></span><span typeof=\"mw:File\"><a href=\"/index.php/%D7%97%D7%91%22%D7%93_%D7%90%D7%95%D7%9F_%D7%9C%D7%99%D7%99%D7%9F\" title=\"חב&quot;ד און ליין\"><img src=\"/images/thumb/8/8c/%D7%A1%D7%99_%D7%90%D7%95_%D7%90%D7%9C_%D7%A1%D7%9E%D7%9C%D7%99%D7%9C.jpg/15px-%D7%A1%D7%99_%D7%90%D7%95_%D7%90%D7%9C_%D7%A1%D7%9E%D7%9C%D7%99%D7%9C.jpg\" decoding=\"async\" width=\"15\" height=\"15\" class=\"mw-file-element\" srcset=\"/images/thumb/8/8c/%D7%A1%D7%99_%D7%90%D7%95_%D7%90%D7%9C_%D7%A1%D7%9E%D7%9C%D7%99%D7%9C.jpg/23px-%D7%A1%D7%99_%D7%90%D7%95_%D7%90%D7%9C_%D7%A1%D7%9E%D7%9C%D7%99%D7%9C.jpg 1.5x, /images/thumb/8/8c/%D7%A1%D7%99_%D7%90%D7%95_%D7%90%D7%9C_%D7%A1%D7%9E%D7%9C%D7%99%D7%9C.jpg/30px-%D7%A1%D7%99_%D7%90%D7%95_%D7%90%D7%9C_%D7%A1%D7%9E%D7%9C%D7%99%D7%9C.jpg 2x\" /></a></span></li>\n<li><a rel=\"nofollow\" class=\"external text\" href=\"https://chabad.info/moshiach/128291/\">השיר של הרב גנזבורג ע\"ה על ימות המשיח</a> <span typeof=\"mw:File\"><a href=\"/index.php/%D7%AA%D7%91%D7%A0%D7%99%D7%AA:%D7%A6%D7%9C%D7%99%D7%9C\" title=\"קובץ שמע\"><img alt=\"קובץ שמע\" src=\"/images/thumb/4/42/%D7%A9%D7%9E%D7%A2.png/16px-%D7%A9%D7%9E%D7%A2.png\" decoding=\"async\" width=\"16\" height=\"16\" class=\"mw-file-element\" srcset=\"/images/thumb/4/42/%D7%A9%D7%9E%D7%A2.png/24px-%D7%A9%D7%9E%D7%A2.png 1.5x, /images/thumb/4/42/%D7%A9%D7%9E%D7%A2.png/32px-%D7%A9%D7%9E%D7%A2.png 2x\" /></a></span><span typeof=\"mw:File\"><a href=\"/index.php/%D7%97%D7%91%22%D7%93_%D7%90%D7%99%D7%A0%D7%A4%D7%95\" title=\"חב&quot;ד אינפו\"><img src=\"/images/thumb/e/ec/%D7%90%D7%99%D7%A0%D7%A4%D7%95.jpg/27px-%D7%90%D7%99%D7%A0%D7%A4%D7%95.jpg\" decoding=\"async\" width=\"27\" height=\"9\" class=\"mw-file-element\" srcset=\"/images/thumb/e/ec/%D7%90%D7%99%D7%A0%D7%A4%D7%95.jpg/41px-%D7%90%D7%99%D7%A0%D7%A4%D7%95.jpg 1.5x, /images/thumb/e/ec/%D7%90%D7%99%D7%A0%D7%A4%D7%95.jpg/54px-%D7%90%D7%99%D7%A0%D7%A4%D7%95.jpg 2x\" /></a></span></li>\n<li><a rel=\"nofollow\" class=\"external text\" href=\"http://shturem.net/index.php?section=news&amp;id=34505\">פרטים נוספים עליו</a> <span typeof=\"mw:File\"><a href=\"/index.php/%D7%A9%D7%98%D7%95%D7%A8%D7%A2%D7%9D_(%D7%90%D7%AA%D7%A8)\" title=\"קישור שטורעם\"><img alt=\"קישור שטורעם\" src=\"/images/thumb/8/89/%D7%A9%D7%98%D7%95%D7%A8%D7%A2%D7%9D.PNG/15px-%D7%A9%D7%98%D7%95%D7%A8%D7%A2%D7%9D.PNG\" decoding=\"async\" width=\"15\" height=\"14\" class=\"mw-file-element\" srcset=\"/images/8/89/%D7%A9%D7%98%D7%95%D7%A8%D7%A2%D7%9D.PNG 1.5x\" /></a></span> <span class=\"grayText\"><small>(הקישור אינו פעיל)</small></span></li></ul>\n<h2><span id=\".D7.94.D7.A2.D7.A8.D7.95.D7.AA_.D7.A9.D7.95.D7.9C.D7.99.D7.99.D7.9D\"></span><span class=\"mw-headline\" id=\"הערות_שוליים\">הערות שוליים</span></h2>\n<div class=\"reflist references-small\">     \n<div class=\"mw-references-wrap\"><ol class=\"references\">\n<li id=\"cite_note-1\"><span class=\"mw-cite-backlink\"><a href=\"#cite_ref-1\">^</a></span> <span class=\"reference-text\">הראשון יצא לאור בשנת <a href=\"/index.php/%D7%AA%D7%A9%22%D7%A0\" title=\"תש&quot;נ\">תש\"נ</a>, והשני בשנת <a href=\"/index.php/%D7%AA%D7%A9%D7%A0%22%D7%91\" title=\"תשנ&quot;ב\">תשנ\"ב</a>.</span>\n</li>\n</ol></div></div>\n<!-- \nNewPP limit report\nCached time: 20260413193620\nCache expiry: 86400\nReduced expiry: false\nComplications: [show‐toc]\nCPU time usage: 0.107 seconds\nReal time usage: 1.563 seconds\nPreprocessor visited node count: 202/1000000\nPost‐expand include size: 1925/2097152 bytes\nTemplate argument size: 682/2097152 bytes\nHighest expansion depth: 8/100\nExpensive parser function count: 3/100\nUnstrip recursion depth: 0/20\nUnstrip post‐expand size: 443/5000000 bytes\nLua time usage: 0.030/7 seconds\nLua virtual size: 5505024/52428800 bytes\nLua estimated memory usage: 0 bytes\n-->\n<!--\nTransclusion expansion time report (%,ms,calls,template)\n100.00%  949.076      1 -total\n 50.85%  482.569      1 תבנית:מפנה\n 19.22%  182.376      1 תבנית:הערה\n 10.29%   97.649      1 תבנית:הערות_שוליים\n  5.77%   54.746      1 תבנית:הערות_שוליים/מרחב_שם\n  5.03%   47.695      1 תבנית:COL\n  4.84%   45.923      1 תבנית:אודיו\n  4.13%   39.218      1 תבנית:אינפו\n  3.30%   31.360      1 תבנית:שטורעם\n  3.02%   28.688      1 תבנית:פירושון\n-->\n\n<!-- Saved in parser cache with key chabadped_1-infopedia_:pcache:idhash:7840-0!canonical and timestamp 20260413193620 and revision id 832521. Rendering was triggered because: page-view\n -->\n</div>"
    },
    "categories": [
      {
        "sortkey": "",
        "*": "חסידים_בתקופת_אדמו\"ר_שליט\"א"
      },
      {
        "sortkey": "",
        "*": "חברי_אגודת_חסידי_חב\"ד_בארץ_הקודש"
      },
      {
        "sortkey": "",
        "*": "בוגרי_אחי_תמימים_תל_אביב"
      },
      {
        "sortkey": "",
        "*": "משפחת_גינזבורג"
      },
      {
        "sortkey": "",
        "*": "חברי_צעירי_אגודת_חב\"ד_בארץ_הקודש"
      },
      {
        "sortkey": "",
        "*": "צוות_רשת_אהלי_יוסף_יצחק"
      },
      {
        "sortkey": "",
        "*": "משפחת_כהן_(2)"
      },
      {
        "sortkey": "",
        "*": "אישים_שנולדו_בשנת_תרפ\"ז"
      },
      {
        "sortkey": "",
        "*": "אישים_שנפטרו_בשנת_תשס\"ו"
      }
    ],
    "links": [
      {
        "ns": 10,
        "exists": "",
        "*": "תבנית:מפנה"
      },
      {
        "ns": 10,
        "exists": "",
        "*": "תבנית:פירושון"
      },
      {
        "ns": 10,
        "exists": "",
        "*": "תבנית:הערות שוליים"
      },
      {
        "ns": 10,
        "exists": "",
        "*": "תבנית:צליל"
      },
      {
        "ns": 0,
        "exists": "",
        "*": "חב\"ד און ליין"
      },
      {
        "ns": 0,
        "exists": "",
        "*": "חב\"ד אינפו"
      },
      {
        "ns": 0,
        "exists": "",
        "*": "שטורעם (אתר)"
      },
      {
        "ns": 0,
        "exists": "",
        "*": "770"
      },
      {
        "ns": 0,
        "exists": "",
        "*": "אברהם ישעיה רייניץ"
      },
      {
        "ns": 0,
        "exists": "",
        "*": "אברהם רייניץ"
      },
      {
        "ns": 0,
        "exists": "",
        "*": "אגודת חסידי חב\"ד באה\"ק"
      },
      {
        "ns": 0,
        "exists": "",
        "*": "אגודת חסידי חב\"ד בארץ הקודש"
      },
      {
        "ns": 0,
        "exists": "",
        "*": "אגרות קודש"
      },
      {
        "ns": 0,
        "exists": "",
        "*": "אחי תמימים תל אביב"
      },
      {
        "ns": 0,
        "exists": "",
        "*": "איגוד תלמידי הישיבות העולמי"
      },
      {
        "ns": 0,
        "exists": "",
        "*": "ארץ הקודש"
      },
      {
        "ns": 0,
        "exists": "",
        "*": "ארצות הברית"
      },
      {
        "ns": 0,
        "exists": "",
        "*": "ב' ניסן"
      },
      {
        "ns": 0,
        "exists": "",
        "*": "ג' תמוז תשנ\"ד"
      },
      {
        "ns": 0,
        "exists": "",
        "*": "האגודה למען הגאולה"
      },
      {
        "ns": 0,
        "exists": "",
        "*": "הרבי"
      },
      {
        "ns": 0,
        "exists": "",
        "*": "הרבי כמלך המשיח"
      },
      {
        "ns": 0,
        "exists": "",
        "*": "הרבי מליובאוויטש כמלך המשיח"
      },
      {
        "ns": 0,
        "exists": "",
        "*": "ועד להפצת שיחות"
      },
      {
        "ns": 0,
        "exists": "",
        "*": "זמרוני ציק"
      },
      {
        "ns": 0,
        "exists": "",
        "*": "חייל בשירות הרבי"
      },
      {
        "ns": 0,
        "exists": "",
        "*": "ט\"ו תמוז"
      },
      {
        "ns": 0,
        "exists": "",
        "*": "י\"ב תמוז"
      },
      {
        "ns": 0,
        "exists": "",
        "*": "י\"ד אדר"
      },
      {
        "ns": 0,
        "exists": "",
        "*": "יואל כהן"
      },
      {
        "ns": 0,
        "exists": "",
        "*": "יצחק גינזבורג (פירושונים)"
      },
      {
        "ns": 0,
        "exists": "",
        "*": "ישראל ברוד"
      },
      {
        "ns": 0,
        "exists": "",
        "*": "כ' כסלו"
      },
      {
        "ns": 0,
        "exists": "",
        "*": "כינוסי גאולה ומשיח - תשנ\"ה"
      },
      {
        "ns": 0,
        "exists": "",
        "*": "כפר חב\"ד"
      },
      {
        "ns": 0,
        "exists": "",
        "*": "לעקאח"
      },
      {
        "ns": 0,
        "exists": "",
        "*": "מבצע מצה לתלמיד"
      },
      {
        "ns": 0,
        "exists": "",
        "*": "מוסקבה"
      },
      {
        "ns": 0,
        "exists": "",
        "*": "מלחמת העולם השנייה"
      },
      {
        "ns": 0,
        "exists": "",
        "*": "משה דובער גנזבורג"
      },
      {
        "ns": 0,
        "exists": "",
        "*": "משיח"
      },
      {
        "ns": 0,
        "exists": "",
        "*": "נצחיות חייו של הרבי"
      },
      {
        "ns": 0,
        "exists": "",
        "*": "ספר התמימים"
      },
      {
        "ns": 0,
        "exists": "",
        "*": "ערב חב\"ד"
      },
      {
        "ns": 0,
        "exists": "",
        "*": "פורים"
      },
      {
        "ns": 0,
        "exists": "",
        "*": "פרסום בשורת הגאולה"
      },
      {
        "ns": 0,
        "exists": "",
        "*": "צא\"ח"
      },
      {
        "ns": 0,
        "exists": "",
        "*": "צבי הירש גנזבורג"
      },
      {
        "ns": 0,
        "exists": "",
        "*": "צה\"ל"
      },
      {
        "ns": 0,
        "exists": "",
        "*": "צעירי אגודת חב\"ד"
      },
      {
        "ns": 0,
        "exists": "",
        "*": "צעירי אגודת חב\"ד בישראל"
      },
      {
        "ns": 0,
        "exists": "",
        "*": "קנדה"
      },
      {
        "ns": 0,
        "exists": "",
        "*": "קראון הייטס"
      },
      {
        "ns": 0,
        "exists": "",
        "*": "רוסיה"
      },
      {
        "ns": 0,
        "exists": "",
        "*": "רפאל נחמן כהן"
      },
      {
        "ns": 0,
        "exists": "",
        "*": "רשת אהלי יוסף יצחק בארץ הקודש"
      },
      {
        "ns": 0,
        "exists": "",
        "*": "שאול ברוק"
      },
      {
        "ns": 0,
        "exists": "",
        "*": "שבועון בית משיח"
      },
      {
        "ns": 0,
        "exists": "",
        "*": "שבע מצוות בני נח"
      },
      {
        "ns": 0,
        "exists": "",
        "*": "שלום יהודה לייב גינזבורג"
      },
      {
        "ns": 0,
        "exists": "",
        "*": "שמועות וסיפורים"
      },
      {
        "ns": 0,
        "exists": "",
        "*": "שניאור זלמן יצחק יהושע חאנין"
      },
      {
        "ns": 0,
        "exists": "",
        "*": "תרפ\"ז"
      },
      {
        "ns": 0,
        "exists": "",
        "*": "תרצ\"ח"
      },
      {
        "ns": 0,
        "exists": "",
        "*": "תש\"י"
      },
      {
        "ns": 0,
        "exists": "",
        "*": "תש\"נ"
      },
      {
        "ns": 0,
        "exists": "",
        "*": "תשי\"ג"
      },
      {
        "ns": 0,
        "exists": "",
        "*": "תשכ\"ד"
      },
      {
        "ns": 0,
        "exists": "",
        "*": "תשל\"ו"
      },
      {
        "ns": 0,
        "exists": "",
        "*": "תשמ\"ט"
      },
      {
        "ns": 0,
        "exists": "",
        "*": "תשנ\"ב"
      },
      {
        "ns": 0,
        "exists": "",
        "*": "תשנ\"ה"
      },
      {
        "ns": 0,
        "exists": "",
        "*": "תשנ\"ט"
      },
      {
        "ns": 0,
        "exists": "",
        "*": "תשס\"ו"
      },
      {
        "ns": 0,
        "*": "גיטל גנזבורג"
      },
      {
        "ns": 0,
        "*": "יוסף גאנזבורג"
      }
    ],
    "sections": [
      {
        "toclevel": 1,
        "level": "2",
        "line": "תולדות חיים",
        "number": "1",
        "index": "1",
        "fromtitle": "יצחק_גנזבורג",
        "byteoffset": 506,
        "anchor": "תולדות_חיים",
        "linkAnchor": "תולדות_חיים"
      },
      {
        "toclevel": 1,
        "level": "2",
        "line": "הספר חייל בשירות הרבי",
        "number": "2",
        "index": "2",
        "fromtitle": "יצחק_גנזבורג",
        "byteoffset": 2303,
        "anchor": "הספר_חייל_בשירות_הרבי",
        "linkAnchor": "הספר_חייל_בשירות_הרבי"
      },
      {
        "toclevel": 1,
        "level": "2",
        "line": "משפחתו",
        "number": "3",
        "index": "3",
        "fromtitle": "יצחק_גנזבורג",
        "byteoffset": 2897,
        "anchor": "משפחתו",
        "linkAnchor": "משפחתו"
      },
      {
        "toclevel": 1,
        "level": "2",
        "line": "קישורים חיצוניים",
        "number": "4",
        "index": "4",
        "fromtitle": "יצחק_גנזבורג",
        "byteoffset": 3419,
        "anchor": "קישורים_חיצוניים",
        "linkAnchor": "קישורים_חיצוניים"
      },
      {
        "toclevel": 1,
        "level": "2",
        "line": "הערות שוליים",
        "number": "5",
        "index": "",
        "byteoffset": null,
        "anchor": "הערות_שוליים",
        "linkAnchor": "הערות_שוליים"
      }
    ],
    "showtoc": ""
  }
}